preserver/__init__.py
preserver/clustering_anonymizer.py
preserver/clustering_preserver.py
preserver/differential_privacy.py
preserver/gv.py
preserver/mondrian_preserver.py
preserver/clustering_utils/__init__.py
preserver/clustering_utils/cluster_init.py
preserver/clustering_utils/clustering.py
preserver/clustering_utils/data_loss.py
preserver/clustering_utils/distance_calculation.py
preserver/clustering_utils/input_validate.py
preserver/clustering_utils/kmodes.py
preserver/mondrian_utils/__init__.py
preserver/mondrian_utils/utility.py
privacy_preserver-1.0.1.dist-info/LICENSE
privacy_preserver-1.0.1.dist-info/METADATA
privacy_preserver-1.0.1.dist-info/WHEEL
privacy_preserver-1.0.1.dist-info/top_level.txt
privacy_preserver-1.0.1.dist-info/RECORD
