Metadata-Version: 2.1
Name: privacy-preserver
Version: 1.0.1
Summary: Anonymizing Library
Home-page: https://github.com/telesoho/privacy-preserver
Author: telesoho
Author-email: telesoho@gmail.com
License: UNKNOWN
Platform: UNKNOWN
Classifier: Programming Language :: Python :: 3
Classifier: License :: OSI Approved :: Apache Software License
Classifier: Operating System :: OS Independent
Requires-Python: >=3.6
License-File: LICENSE
Requires-Dist: pandas (>=1.3.2)
Requires-Dist: numpy (>=1.21.2)
Requires-Dist: kmodes
